[
 
       
       
         {
           "res": "FHD",
           "sound": "Vie",
           "teams":  "France Vs Denmark",
           "link": "https://yypull.gdsth.com/live/stream-556802.m3u8?auth_key=1669498822-0-0-4ff06a4580aa0f812a988e0e8d608f36"
         } , 
         {
           "res": "FHD",
           "sound": "Vie",
           "teams":    "France Vs Denmark",
           "link": "https://live-ali4.tv360.vn/manifest/VTV6_HD/playlist_720p.m3u8"
         },
         {
           "res": "HD",
           "sound": "China",
           "teams":   "France Vs Denmark",
           "link": "https://pullalilive.livnvess.com/live/stream-115493.m3u8?auth_key=1669248931-0-0-7121e2b13f05458765bf17ecf0bc9799"
        },  
        {
           "res": "FHD",
           "sound": "Vie",
           "teams":  "Argentina Vs Mexico",
           "link": "https://canyou.letmestreamyou.net/live/itvuk_720p/index.m3u8"
         } , 
         {
           "res": "FHD",
           "sound": "Vie",
           "teams":    "Argentina Vs Mexico",
           "link": ""
         },
         {
           "res": "HD",
           "sound": "China",
           "teams":  "Argentina Vs Mexico",
           "link": ""
         }, 
         {
           "res": "FHD",
           "sound": "Vie",
           "teams":  "Japan Vs Costa Rica",
           "link": ""
         } , 
         {
           "res": "FHD",
           "sound": "Vie",
           "teams":    "Japan Vs Costa Rica",
           "link": ""
         },
         {
           "res": "HD",
           "sound": "China",
           "teams":   "Japan Vs Costa Rica",
           "link": ""
        },  
        {
           "res": "FHD",
           "sound": "Vie",
           "teams":  "Belgium Vs Morocco",
           "link": ""
         } , 
         {
           "res": "FHD",
           "sound": "Vie",
           "teams":   "Belgium Vs Morocco",
           "link": ""
         },
         {
           "res": "HD",
           "sound": "China",
           "teams":  "Belgium Vs Morocco",
           "link": ""
        }, 
         {
           "res": "FHD",
           "sound": "Vie",
           "teams":  "Croatia Vs Canada",
           "link": ""
         } , 
         {
           "res": "FHD",
           "sound": "Vie",
           "teams":   "Croatia Vs Canada",
           "link": ""
         },
         {
           "res": "HD",
           "sound": "China",
           "teams":  "Croatia Vs Canada",
           "link": ""
        },  
        {
           "res": "FHD",
           "sound": "Vie",
           "teams":  "Spain Vs Germany",
           "link": ""
         } , 
         {
           "res": "FHD",
           "sound": "Vie",
           "teams":   "Spain Vs Germany",
           "link": ""
         },
         {
           "res": "HD",
           "sound": "China",
           "teams":  "Spain Vs Germany",
           "link": ""
        }    
   ]
    
   
        
    
    
     
