[
{
           "res": "Sd",
           "sound": "China",
           "teams": "Nottm Vs Liver",
           "link": "https://yypull.gdsth.com/live/stream-308116.m3u8?auth_key=1666458557-0-0-2ef7edbb97c9d37d29435a6ae3033f2f"

         },
           {
           "res": "HD",
           "sound": "vie",
           "teams": "Nottm Vs Liver",
           "link": "https://pullalilive.livnvess.com/live/stream-218821.m3u8?auth_key=1666458808-0-0-78c058c942c8bd93b5162b42750cb854"

         },
           {
           "res": "FHD",
           "sound": "Vie",
           "teams": "Union Vs Dort",
           "link": "https://pullalilive.livnvess.com/live/stream-132385.m3u8?auth_key=1665954387-0-0-fca1c4317ea03e30e30e8dea659c0a7c"

         }
           
          
           
           
           
]
