[
 
       
       
         {
           "res": "FHD",
           "sound": "Chinese",
           "teams":  "CAM VS BRA",
           "link":  ""
         } , 
         {
           "res": "FHD",
           "sound":  "Vietnam",
           "teams":    "CAM VS BRA",
           "link":    ""
         },
         {
           "res": "FHD",
           "sound": "English",
           "teams":    "CAM VS BRA",
           "link":  ""
         },
         {
           "res": "FHD",
           "sound": "English",
           "teams": "CAM VS BRA",
           "link":  ""
         } , 
         {
           "res": "HD",
           "sound":  "Arabic",
           "teams":   "CAM VS BRA",
           "link":  ""
         },
         {
           "res": "FHD",
           "sound": "Chinese",
           "teams":   "SER VS SWI",
           "link":  ""
        }, 
         {
           "res": "FHD",
           "sound":  "Vietnam",
           "teams":     "SER VS SWI",
           "link":    ""
         },
         {
           "res": "FHD",
           "sound": "English",
           "teams":    "SER VS SWI",
           "link":  ""
         },
         {
           "res": "FHD",
           "sound":  "English",
           "teams":   "SER VS SWI",
           "link":  ""
         } , 
         {
           "res": "HD",
           "sound":  "Arabic",
           "teams":    "SER VS SWI",
           "link":  ""
         }
        
     ]
    
   
        
    
    
     
