[ 
  {
           "res": "FHD",
           "sound": "Vie",
           "teams":   "England Vs Iran ",
           "link": "https://moon.meta-scores.com/e1f88c86c7_fhd2/e1f88c86c7_fhd2@720p.m3u8"
        },
        {
           "res": "FHD",
           "sound": "China",
           "teams":  "England Vs Iran ",,
           "link": "https://yypull.gdsth.com/live/stream-330076.m3u8?auth_key=1669056322-0-0-8a1cd61fd0dc3cb8fed05bd61cfcd549"
        } ,
        {
           "res": "FHD",
           "sound": "china",
           "teams":  "England Vs Iran ",
           "link": "https://pullalilive.livnvess.com/live/stream-167414.m3u8?auth_key=1669055431-0-0-92ecb350e7e8fde8d44b7a5528564a48"
        },
        {
           "res": "FHD",
           "sound": "Vie",
           "teams":  "Senegal Vs Netherlands",
           "link": ""
        }, 
        {
           "res": "FHD",
           "sound": "Vie",
           "teams":  "Senegal Vs Netherlands",
           "link": ""
        },
         {
           "res": "FHD",
           "sound": "China",
           "teams":  "Senegal vs Netherlands",
           "link": ""
        }, 
        {
           "res": "HD",
           "sound": "Vie",
           "teams":  "USA Vs Wales",
           "link": ""
        }, 
        {
           "res": "HD",
           "sound": "Vie",
           "teams":  "USA Vs Wales",
           "link": ""
        },
        {
           "res": "HD",
           "sound": "China",
           "teams":  "USA Vs Wales",
           "link": ""
        },
         {
           "res": "FHD",
           "sound": "Vie",
           "teams":  "Argentina Vs Saudi",
           "link": ""
        }, 
        {
           "res": "FHD",
           "sound": "China",
           "teams":  "Argentina Vs Saudi",
           "link": ""
        },
        {
           "res": "FHD",
           "sound": "China",
           "teams":  "Argentina Vs Saudi",
           "link": ""
        }, 
        {
           "res": "FHD",
           "sound": "Vie",
           "teams":  "Denmark Vs Tunisia",
           "link": ""
        },
        {
           "res": "FHD",
           "sound": "Vie",
           "teams":  "Denmark Vs Tunisia",
           "link": ""
        }, 
        {
           "res": "FHD",
           "sound": "China",
           "teams":  "Denmark Vs Tunisia",
           "link": ""
        } ,
         {
           "res": "FHD",
           "sound": "Vie",
           "teams":  "Mexico Vs Poland",
           "link": ""
        } , 
        {
           "res": "FHD",
           "sound": "Vie",
           "teams":  "Mexico Vs Poland",
           "link": ""
        } , 
        {
           "res": "FHD",
           "sound": "China",
           "teams":  "Mexico Vs Poland",
           "link": ""
        } , 
        {
           "res": "FHD",
           "sound": "Vie",
           "teams":  "France Vs Australia",
           "link": ""
        } ,  
        {
           "res": "FHD",
           "sound": "Vie",
           "teams":  "France Vs Australia",
           "link": ""
        } , 
        {
           "res": "FHD",
           "sound": "China",
           "teams":  "France Vs Australia",
           "link": ""
        } 
  ]     
    
   
        
    
    
     
